{
    "edges": [
        {
            "from": "26",
            "label": "5",
            "to": "6"
        },
        {
            "from": "26",
            "label": "5",
            "to": "21"
        },
        {
            "from": "26",
            "label": "5",
            "to": "39"
        },
        {
            "from": "26",
            "label": "3",
            "to": "36"
        },
        {
            "from": "25",
            "label": "4",
            "to": "17"
        },
        {
            "from": "25",
            "label": "3",
            "to": "22"
        },
        {
            "from": "25",
            "label": "5",
            "to": "4"
        },
        {
            "from": "25",
            "label": "5",
            "to": "5"
        },
        {
            "from": "25",
            "label": "4",
            "to": "14"
        },
        {
            "from": "25",
            "label": "3",
            "to": "2"
        },
        {
            "from": "25",
            "label": "4",
            "to": "30"
        },
        {
            "from": "25",
            "label": "5",
            "to": "34"
        },
        {
            "from": "25",
            "label": "3",
            "to": "25"
        },
        {
            "from": "25",
            "label": "5",
            "to": "20"
        },
        {
            "from": "25",
            "label": "4",
            "to": "8"
        },
        {
            "from": "25",
            "label": "4",
            "to": "31"
        },
        {
            "from": "25",
            "label": "5",
            "to": "36"
        },
        {
            "from": "25",
            "label": "5",
            "to": "24"
        },
        {
            "from": "25",
            "label": "5",
            "to": "26"
        },
        {
            "from": "25",
            "label": "5",
            "to": "13"
        },
        {
            "from": "25",
            "label": "3",
            "to": "16"
        },
        {
            "from": "25",
            "label": "4",
            "to": "7"
        },
        {
            "from": "25",
            "label": "5",
            "to": "40"
        },
        {
            "from": "25",
            "label": "5",
            "to": "3"
        },
        {
            "from": "25",
            "label": "5",
            "to": "29"
        },
        {
            "from": "25",
            "label": "5",
            "to": "6"
        },
        {
            "from": "25",
            "label": "3",
            "to": "15"
        },
        {
            "from": "25",
            "label": "5",
            "to": "12"
        },
        {
            "from": "25",
            "label": "3",
            "to": "10"
        },
        {
            "from": "25",
            "label": "3",
            "to": "1"
        },
        {
            "from": "25",
            "label": "5",
            "to": "27"
        },
        {
            "from": "25",
            "label": "5",
            "to": "39"
        },
        {
            "from": "24",
            "label": "3",
            "to": "21"
        },
        {
            "from": "24",
            "label": "4",
            "to": "6"
        },
        {
            "from": "24",
            "label": "3",
            "to": "39"
        },
        {
            "from": "24",
            "label": "5",
            "to": "29"
        },
        {
            "from": "24",
            "label": "4",
            "to": "35"
        },
        {
            "from": "24",
            "label": "3",
            "to": "14"
        },
        {
            "from": "24",
            "label": "4",
            "to": "33"
        },
        {
            "from": "24",
            "label": "5",
            "to": "1"
        },
        {
            "from": "24",
            "label": "4",
            "to": "20"
        },
        {
            "from": "24",
            "label": "3",
            "to": "7"
        },
        {
            "from": "24",
            "label": "4",
            "to": "32"
        },
        {
            "from": "24",
            "label": "5",
            "to": "24"
        },
        {
            "from": "24",
            "label": "5",
            "to": "23"
        },
        {
            "from": "24",
            "label": "4",
            "to": "25"
        },
        {
            "from": "24",
            "label": "3",
            "to": "38"
        },
        {
            "from": "24",
            "label": "5",
            "to": "4"
        },
        {
            "from": "24",
            "label": "5",
            "to": "18"
        },
        {
            "from": "24",
            "label": "3",
            "to": "5"
        },
        {
            "from": "24",
            "label": "5",
            "to": "2"
        },
        {
            "from": "24",
            "label": "5",
            "to": "10"
        },
        {
            "from": "24",
            "label": "5",
            "to": "37"
        },
        {
            "from": "24",
            "label": "4",
            "to": "3"
        },
        {
            "from": "24",
            "label": "5",
            "to": "8"
        },
        {
            "from": "24",
            "label": "4",
            "to": "31"
        },
        {
            "from": "24",
            "label": "4",
            "to": "9"
        },
        {
            "from": "24",
            "label": "3",
            "to": "17"
        },
        {
            "from": "24",
            "label": "5",
            "to": "40"
        },
        {
            "from": "24",
            "label": "5",
            "to": "19"
        },
        {
            "from": "24",
            "label": "5",
            "to": "27"
        },
        {
            "from": "23",
            "label": "5",
            "to": "30"
        },
        {
            "from": "23",
            "label": "5",
            "to": "36"
        },
        {
            "from": "23",
            "label": "3",
            "to": "40"
        },
        {
            "from": "23",
            "label": "5",
            "to": "32"
        },
        {
            "from": "23",
            "label": "5",
            "to": "33"
        },
        {
            "from": "23",
            "label": "4",
            "to": "4"
        },
        {
            "from": "23",
            "label": "4",
            "to": "7"
        },
        {
            "from": "23",
            "label": "5",
            "to": "29"
        },
        {
            "from": "23",
            "label": "5",
            "to": "38"
        },
        {
            "from": "23",
            "label": "3",
            "to": "3"
        },
        {
            "from": "23",
            "label": "4",
            "to": "22"
        },
        {
            "from": "23",
            "label": "3",
            "to": "14"
        },
        {
            "from": "23",
            "label": "3",
            "to": "1"
        },
        {
            "from": "23",
            "label": "5",
            "to": "27"
        },
        {
            "from": "23",
            "label": "5",
            "to": "17"
        },
        {
            "from": "23",
            "label": "4",
            "to": "18"
        },
        {
            "from": "23",
            "label": "3",
            "to": "28"
        },
        {
            "from": "23",
            "label": "3",
            "to": "15"
        },
        {
            "from": "23",
            "label": "5",
            "to": "25"
        },
        {
            "from": "23",
            "label": "5",
            "to": "6"
        },
        {
            "from": "23",
            "label": "3",
            "to": "2"
        },
        {
            "from": "23",
            "label": "5",
            "to": "5"
        },
        {
            "from": "22",
            "label": "5",
            "to": "35"
        },
        {
            "from": "22",
            "label": "5",
            "to": "23"
        },
        {
            "from": "22",
            "label": "4",
            "to": "19"
        },
        {
            "from": "22",
            "label": "3",
            "to": "16"
        },
        {
            "from": "22",
            "label": "4",
            "to": "9"
        },
        {
            "from": "22",
            "label": "5",
            "to": "2"
        },
        {
            "from": "22",
            "label": "5",
            "to": "36"
        },
        {
            "from": "22",
            "label": "4",
            "to": "24"
        },
        {
            "from": "22",
            "label": "3",
            "to": "18"
        },
        {
            "from": "22",
            "label": "3",
            "to": "26"
        },
        {
            "from": "22",
            "label": "5",
            "to": "27"
        },
        {
            "from": "22",
            "label": "5",
            "to": "37"
        },
        {
            "from": "22",
            "label": "4",
            "to": "38"
        },
        {
            "from": "22",
            "label": "5",
            "to": "39"
        },
        {
            "from": "22",
            "label": "5",
            "to": "40"
        },
        {
            "from": "22",
            "label": "4",
            "to": "10"
        },
        {
            "from": "22",
            "label": "3",
            "to": "34"
        },
        {
            "from": "22",
            "label": "5",
            "to": "30"
        },
        {
            "from": "22",
            "label": "3",
            "to": "20"
        },
        {
            "from": "22",
            "label": "5",
            "to": "5"
        },
        {
            "from": "22",
            "label": "5",
            "to": "12"
        },
        {
            "from": "22",
            "label": "5",
            "to": "21"
        },
        {
            "from": "22",
            "label": "5",
            "to": "13"
        },
        {
            "from": "22",
            "label": "3",
            "to": "25"
        },
        {
            "from": "22",
            "label": "3",
            "to": "14"
        },
        {
            "from": "22",
            "label": "4",
            "to": "31"
        },
        {
            "from": "22",
            "label": "5",
            "to": "17"
        },
        {
            "from": "22",
            "label": "5",
            "to": "15"
        },
        {
            "from": "21",
            "label": "5",
            "to": "29"
        },
        {
            "from": "21",
            "label": "4",
            "to": "22"
        },
        {
            "from": "21",
            "label": "4",
            "to": "40"
        },
        {
            "from": "21",
            "label": "5",
            "to": "2"
        },
        {
            "from": "21",
            "label": "5",
            "to": "8"
        },
        {
            "from": "21",
            "label": "4",
            "to": "20"
        },
        {
            "from": "21",
            "label": "3",
            "to": "3"
        },
        {
            "from": "21",
            "label": "5",
            "to": "1"
        },
        {
            "from": "21",
            "label": "4",
            "to": "5"
        },
        {
            "from": "21",
            "label": "4",
            "to": "33"
        },
        {
            "from": "21",
            "label": "5",
            "to": "31"
        },
        {
            "from": "21",
            "label": "5",
            "to": "37"
        },
        {
            "from": "21",
            "label": "5",
            "to": "39"
        },
        {
            "from": "21",
            "label": "3",
            "to": "28"
        },
        {
            "from": "21",
            "label": "4",
            "to": "35"
        },
        {
            "from": "21",
            "label": "3",
            "to": "18"
        },
        {
            "from": "21",
            "label": "5",
            "to": "6"
        },
        {
            "from": "21",
            "label": "5",
            "to": "34"
        },
        {
            "from": "21",
            "label": "5",
            "to": "13"
        },
        {
            "from": "21",
            "label": "5",
            "to": "32"
        },
        {
            "from": "20",
            "label": "3",
            "to": "17"
        },
        {
            "from": "20",
            "label": "3",
            "to": "5"
        },
        {
            "from": "20",
            "label": "3",
            "to": "40"
        },
        {
            "from": "20",
            "label": "4",
            "to": "32"
        },
        {
            "from": "20",
            "label": "4",
            "to": "1"
        },
        {
            "from": "20",
            "label": "3",
            "to": "26"
        },
        {
            "from": "20",
            "label": "3",
            "to": "10"
        },
        {
            "from": "20",
            "label": "3",
            "to": "15"
        },
        {
            "from": "20",
            "label": "5",
            "to": "30"
        },
        {
            "from": "20",
            "label": "5",
            "to": "14"
        },
        {
            "from": "20",
            "label": "3",
            "to": "20"
        },
        {
            "from": "20",
            "label": "5",
            "to": "38"
        },
        {
            "from": "20",
            "label": "5",
            "to": "36"
        },
        {
            "from": "20",
            "label": "3",
            "to": "4"
        },
        {
            "from": "20",
            "label": "5",
            "to": "16"
        },
        {
            "from": "20",
            "label": "5",
            "to": "31"
        },
        {
            "from": "20",
            "label": "5",
            "to": "3"
        },
        {
            "from": "20",
            "label": "3",
            "to": "27"
        },
        {
            "from": "20",
            "label": "3",
            "to": "21"
        },
        {
            "from": "20",
            "label": "5",
            "to": "2"
        },
        {
            "from": "20",
            "label": "3",
            "to": "33"
        },
        {
            "from": "20",
            "label": "5",
            "to": "7"
        },
        {
            "from": "20",
            "label": "4",
            "to": "28"
        },
        {
            "from": "20",
            "label": "5",
            "to": "22"
        },
        {
            "from": "20",
            "label": "5",
            "to": "19"
        },
        {
            "from": "20",
            "label": "4",
            "to": "11"
        },
        {
            "from": "20",
            "label": "4",
            "to": "12"
        },
        {
            "from": "20",
            "label": "5",
            "to": "34"
        },
        {
            "from": "19",
            "label": "3",
            "to": "17"
        },
        {
            "from": "19",
            "label": "5",
            "to": "15"
        },
        {
            "from": "19",
            "label": "3",
            "to": "9"
        },
        {
            "from": "19",
            "label": "4",
            "to": "36"
        },
        {
            "from": "19",
            "label": "5",
            "to": "4"
        },
        {
            "from": "19",
            "label": "4",
            "to": "11"
        },
        {
            "from": "19",
            "label": "3",
            "to": "6"
        },
        {
            "from": "19",
            "label": "5",
            "to": "27"
        },
        {
            "from": "19",
            "label": "5",
            "to": "26"
        },
        {
            "from": "19",
            "label": "5",
            "to": "35"
        },
        {
            "from": "19",
            "label": "5",
            "to": "38"
        },
        {
            "from": "19",
            "label": "4",
            "to": "23"
        },
        {
            "from": "19",
            "label": "5",
            "to": "10"
        },
        {
            "from": "19",
            "label": "3",
            "to": "16"
        },
        {
            "from": "19",
            "label": "5",
            "to": "31"
        },
        {
            "from": "19",
            "label": "3",
            "to": "13"
        },
        {
            "from": "19",
            "label": "3",
            "to": "24"
        },
        {
            "from": "19",
            "label": "3",
            "to": "39"
        },
        {
            "from": "19",
            "label": "5",
            "to": "21"
        },
        {
            "from": "19",
            "label": "5",
            "to": "25"
        },
        {
            "from": "19",
            "label": "4",
            "to": "37"
        },
        {
            "from": "19",
            "label": "5",
            "to": "33"
        },
        {
            "from": "19",
            "label": "5",
            "to": "14"
        },
        {
            "from": "19",
            "label": "4",
            "to": "18"
        },
        {
            "from": "19",
            "label": "5",
            "to": "12"
        },
        {
            "from": "19",
            "label": "3",
            "to": "34"
        },
        {
            "from": "19",
            "label": "5",
            "to": "8"
        },
        {
            "from": "19",
            "label": "4",
            "to": "2"
        },
        {
            "from": "18",
            "label": "3",
            "to": "34"
        },
        {
            "from": "18",
            "label": "3",
            "to": "30"
        },
        {
            "from": "18",
            "label": "4",
            "to": "25"
        },
        {
            "from": "18",
            "label": "3",
            "to": "27"
        },
        {
            "from": "18",
            "label": "4",
            "to": "18"
        },
        {
            "from": "18",
            "label": "5",
            "to": "11"
        },
        {
            "from": "18",
            "label": "3",
            "to": "28"
        },
        {
            "from": "18",
            "label": "5",
            "to": "9"
        },
        {
            "from": "18",
            "label": "5",
            "to": "19"
        },
        {
            "from": "18",
            "label": "5",
            "to": "6"
        },
        {
            "from": "18",
            "label": "4",
            "to": "38"
        },
        {
            "from": "18",
            "label": "4",
            "to": "36"
        },
        {
            "from": "18",
            "label": "4",
            "to": "15"
        },
        {
            "from": "18",
            "label": "5",
            "to": "35"
        },
        {
            "from": "18",
            "label": "5",
            "to": "40"
        },
        {
            "from": "18",
            "label": "5",
            "to": "24"
        },
        {
            "from": "18",
            "label": "3",
            "to": "26"
        },
        {
            "from": "18",
            "label": "5",
            "to": "12"
        },
        {
            "from": "18",
            "label": "5",
            "to": "4"
        },
        {
            "from": "18",
            "label": "5",
            "to": "1"
        },
        {
            "from": "18",
            "label": "3",
            "to": "32"
        },
        {
            "from": "18",
            "label": "5",
            "to": "22"
        },
        {
            "from": "17",
            "label": "5",
            "to": "20"
        },
        {
            "from": "17",
            "label": "5",
            "to": "14"
        },
        {
            "from": "17",
            "label": "5",
            "to": "28"
        },
        {
            "from": "17",
            "label": "5",
            "to": "6"
        },
        {
            "from": "17",
            "label": "5",
            "to": "11"
        },
        {
            "from": "17",
            "label": "5",
            "to": "18"
        },
        {
            "from": "17",
            "label": "5",
            "to": "35"
        },
        {
            "from": "17",
            "label": "3",
            "to": "23"
        },
        {
            "from": "17",
            "label": "5",
            "to": "3"
        },
        {
            "from": "17",
            "label": "4",
            "to": "22"
        },
        {
            "from": "17",
            "label": "5",
            "to": "32"
        },
        {
            "from": "17",
            "label": "5",
            "to": "29"
        },
        {
            "from": "17",
            "label": "3",
            "to": "17"
        },
        {
            "from": "17",
            "label": "5",
            "to": "27"
        },
        {
            "from": "17",
            "label": "4",
            "to": "38"
        },
        {
            "from": "17",
            "label": "5",
            "to": "1"
        },
        {
            "from": "17",
            "label": "5",
            "to": "37"
        },
        {
            "from": "17",
            "label": "5",
            "to": "40"
        },
        {
            "from": "17",
            "label": "3",
            "to": "12"
        },
        {
            "from": "17",
            "label": "4",
            "to": "19"
        },
        {
            "from": "17",
            "label": "5",
            "to": "34"
        },
        {
            "from": "17",
            "label": "4",
            "to": "25"
        },
        {
            "from": "16",
            "label": "5",
            "to": "8"
        },
        {
            "from": "16",
            "label": "4",
            "to": "4"
        },
        {
            "from": "16",
            "label": "4",
            "to": "7"
        },
        {
            "from": "16",
            "label": "5",
            "to": "33"
        },
        {
            "from": "16",
            "label": "5",
            "to": "20"
        },
        {
            "from": "16",
            "label": "5",
            "to": "13"
        },
        {
            "from": "16",
            "label": "5",
            "to": "16"
        },
        {
            "from": "16",
            "label": "5",
            "to": "1"
        },
        {
            "from": "16",
            "label": "5",
            "to": "25"
        },
        {
            "from": "16",
            "label": "4",
            "to": "9"
        },
        {
            "from": "16",
            "label": "5",
            "to": "30"
        },
        {
            "from": "16",
            "label": "5",
            "to": "22"
        },
        {
            "from": "16",
            "label": "5",
            "to": "14"
        },
        {
            "from": "16",
            "label": "4",
            "to": "18"
        },
        {
            "from": "16",
            "label": "4",
            "to": "24"
        },
        {
            "from": "16",
            "label": "4",
            "to": "2"
        },
        {
            "from": "16",
            "label": "5",
            "to": "15"
        },
        {
            "from": "16",
            "label": "5",
            "to": "32"
        },
        {
            "from": "16",
            "label": "5",
            "to": "11"
        },
        {
            "from": "16",
            "label": "5",
            "to": "3"
        },
        {
            "from": "15",
            "label": "5",
            "to": "11"
        },
        {
            "from": "15",
            "label": "3",
            "to": "28"
        },
        {
            "from": "15",
            "label": "3",
            "to": "4"
        },
        {
            "from": "15",
            "label": "5",
            "to": "22"
        },
        {
            "from": "15",
            "label": "3",
            "to": "14"
        },
        {
            "from": "15",
            "label": "4",
            "to": "15"
        },
        {
            "from": "15",
            "label": "5",
            "to": "24"
        },
        {
            "from": "15",
            "label": "5",
            "to": "17"
        },
        {
            "from": "15",
            "label": "5",
            "to": "8"
        },
        {
            "from": "15",
            "label": "4",
            "to": "29"
        },
        {
            "from": "15",
            "label": "3",
            "to": "6"
        },
        {
            "from": "15",
            "label": "3",
            "to": "35"
        },
        {
            "from": "15",
            "label": "3",
            "to": "36"
        },
        {
            "from": "15",
            "label": "5",
            "to": "23"
        },
        {
            "from": "15",
            "label": "5",
            "to": "30"
        },
        {
            "from": "15",
            "label": "3",
            "to": "39"
        },
        {
            "from": "15",
            "label": "5",
            "to": "5"
        },
        {
            "from": "15",
            "label": "5",
            "to": "1"
        },
        {
            "from": "15",
            "label": "5",
            "to": "32"
        },
        {
            "from": "15",
            "label": "5",
            "to": "33"
        },
        {
            "from": "14",
            "label": "4",
            "to": "12"
        },
        {
            "from": "14",
            "label": "3",
            "to": "1"
        },
        {
            "from": "14",
            "label": "3",
            "to": "37"
        },
        {
            "from": "14",
            "label": "5",
            "to": "2"
        },
        {
            "from": "14",
            "label": "3",
            "to": "13"
        },
        {
            "from": "14",
            "label": "4",
            "to": "28"
        },
        {
            "from": "14",
            "label": "5",
            "to": "29"
        },
        {
            "from": "14",
            "label": "5",
            "to": "39"
        },
        {
            "from": "14",
            "label": "5",
            "to": "35"
        },
        {
            "from": "14",
            "label": "4",
            "to": "26"
        },
        {
            "from": "14",
            "label": "4",
            "to": "18"
        },
        {
            "from": "14",
            "label": "4",
            "to": "16"
        },
        {
            "from": "14",
            "label": "4",
            "to": "32"
        },
        {
            "from": "14",
            "label": "4",
            "to": "23"
        },
        {
            "from": "14",
            "label": "4",
            "to": "22"
        },
        {
            "from": "14",
            "label": "4",
            "to": "20"
        },
        {
            "from": "14",
            "label": "4",
            "to": "11"
        },
        {
            "from": "14",
            "label": "4",
            "to": "10"
        },
        {
            "from": "14",
            "label": "3",
            "to": "30"
        },
        {
            "from": "14",
            "label": "5",
            "to": "21"
        },
        {
            "from": "13",
            "label": "3",
            "to": "26"
        },
        {
            "from": "13",
            "label": "5",
            "to": "11"
        },
        {
            "from": "13",
            "label": "3",
            "to": "23"
        },
        {
            "from": "13",
            "label": "5",
            "to": "37"
        },
        {
            "from": "13",
            "label": "3",
            "to": "32"
        },
        {
            "from": "13",
            "label": "5",
            "to": "33"
        },
        {
            "from": "13",
            "label": "5",
            "to": "6"
        },
        {
            "from": "13",
            "label": "5",
            "to": "35"
        },
        {
            "from": "13",
            "label": "3",
            "to": "8"
        },
        {
            "from": "13",
            "label": "3",
            "to": "28"
        },
        {
            "from": "13",
            "label": "3",
            "to": "22"
        },
        {
            "from": "13",
            "label": "5",
            "to": "9"
        },
        {
            "from": "13",
            "label": "5",
            "to": "16"
        },
        {
            "from": "13",
            "label": "5",
            "to": "10"
        },
        {
            "from": "13",
            "label": "5",
            "to": "24"
        },
        {
            "from": "13",
            "label": "5",
            "to": "20"
        },
        {
            "from": "13",
            "label": "5",
            "to": "40"
        },
        {
            "from": "13",
            "label": "5",
            "to": "39"
        },
        {
            "from": "13",
            "label": "5",
            "to": "7"
        },
        {
            "from": "13",
            "label": "5",
            "to": "27"
        },
        {
            "from": "13",
            "label": "5",
            "to": "12"
        },
        {
            "from": "13",
            "label": "5",
            "to": "14"
        },
        {
            "from": "13",
            "label": "5",
            "to": "1"
        },
        {
            "from": "13",
            "label": "3",
            "to": "34"
        },
        {
            "from": "13",
            "label": "5",
            "to": "19"
        },
        {
            "from": "13",
            "label": "4",
            "to": "18"
        },
        {
            "from": "12",
            "label": "4",
            "to": "13"
        },
        {
            "from": "12",
            "label": "4",
            "to": "14"
        },
        {
            "from": "12",
            "label": "5",
            "to": "15"
        },
        {
            "from": "12",
            "label": "5",
            "to": "11"
        },
        {
            "from": "12",
            "label": "5",
            "to": "32"
        },
        {
            "from": "12",
            "label": "5",
            "to": "39"
        },
        {
            "from": "12",
            "label": "5",
            "to": "34"
        },
        {
            "from": "12",
            "label": "5",
            "to": "25"
        },
        {
            "from": "12",
            "label": "5",
            "to": "19"
        },
        {
            "from": "12",
            "label": "5",
            "to": "3"
        },
        {
            "from": "12",
            "label": "4",
            "to": "33"
        },
        {
            "from": "12",
            "label": "4",
            "to": "35"
        },
        {
            "from": "12",
            "label": "3",
            "to": "31"
        },
        {
            "from": "12",
            "label": "4",
            "to": "28"
        },
        {
            "from": "12",
            "label": "4",
            "to": "22"
        },
        {
            "from": "12",
            "label": "5",
            "to": "40"
        },
        {
            "from": "12",
            "label": "5",
            "to": "21"
        },
        {
            "from": "12",
            "label": "5",
            "to": "18"
        },
        {
            "from": "12",
            "label": "4",
            "to": "30"
        },
        {
            "from": "12",
            "label": "5",
            "to": "8"
        },
        {
            "from": "12",
            "label": "5",
            "to": "29"
        },
        {
            "from": "12",
            "label": "5",
            "to": "4"
        },
        {
            "from": "12",
            "label": "4",
            "to": "27"
        },
        {
            "from": "12",
            "label": "4",
            "to": "9"
        },
        {
            "from": "12",
            "label": "5",
            "to": "16"
        },
        {
            "from": "12",
            "label": "5",
            "to": "23"
        },
        {
            "from": "12",
            "label": "4",
            "to": "36"
        },
        {
            "from": "12",
            "label": "3",
            "to": "20"
        },
        {
            "from": "11",
            "label": "3",
            "to": "16"
        },
        {
            "from": "11",
            "label": "5",
            "to": "13"
        },
        {
            "from": "11",
            "label": "3",
            "to": "14"
        },
        {
            "from": "11",
            "label": "5",
            "to": "4"
        },
        {
            "from": "11",
            "label": "5",
            "to": "40"
        },
        {
            "from": "11",
            "label": "5",
            "to": "25"
        },
        {
            "from": "11",
            "label": "5",
            "to": "35"
        },
        {
            "from": "11",
            "label": "4",
            "to": "27"
        },
        {
            "from": "11",
            "label": "3",
            "to": "6"
        },
        {
            "from": "11",
            "label": "3",
            "to": "30"
        },
        {
            "from": "11",
            "label": "5",
            "to": "32"
        },
        {
            "from": "11",
            "label": "5",
            "to": "19"
        },
        {
            "from": "11",
            "label": "3",
            "to": "11"
        },
        {
            "from": "11",
            "label": "4",
            "to": "5"
        },
        {
            "from": "11",
            "label": "5",
            "to": "8"
        },
        {
            "from": "11",
            "label": "5",
            "to": "20"
        },
        {
            "from": "11",
            "label": "5",
            "to": "36"
        },
        {
            "from": "11",
            "label": "4",
            "to": "9"
        },
        {
            "from": "11",
            "label": "3",
            "to": "12"
        },
        {
            "from": "11",
            "label": "3",
            "to": "18"
        },
        {
            "from": "11",
            "label": "5",
            "to": "23"
        },
        {
            "from": "10",
            "label": "5",
            "to": "16"
        },
        {
            "from": "10",
            "label": "4",
            "to": "26"
        },
        {
            "from": "10",
            "label": "5",
            "to": "10"
        },
        {
            "from": "10",
            "label": "4",
            "to": "34"
        },
        {
            "from": "10",
            "label": "4",
            "to": "11"
        },
        {
            "from": "10",
            "label": "4",
            "to": "4"
        },
        {
            "from": "10",
            "label": "3",
            "to": "15"
        },
        {
            "from": "10",
            "label": "5",
            "to": "3"
        },
        {
            "from": "10",
            "label": "3",
            "to": "5"
        },
        {
            "from": "10",
            "label": "3",
            "to": "8"
        },
        {
            "from": "10",
            "label": "3",
            "to": "37"
        },
        {
            "from": "10",
            "label": "4",
            "to": "38"
        },
        {
            "from": "10",
            "label": "3",
            "to": "2"
        },
        {
            "from": "10",
            "label": "5",
            "to": "17"
        },
        {
            "from": "10",
            "label": "5",
            "to": "7"
        },
        {
            "from": "10",
            "label": "3",
            "to": "1"
        },
        {
            "from": "10",
            "label": "5",
            "to": "19"
        },
        {
            "from": "10",
            "label": "5",
            "to": "29"
        },
        {
            "from": "10",
            "label": "5",
            "to": "40"
        },
        {
            "from": "10",
            "label": "5",
            "to": "32"
        },
        {
            "from": "10",
            "label": "3",
            "to": "20"
        },
        {
            "from": "10",
            "label": "5",
            "to": "30"
        },
        {
            "from": "10",
            "label": "4",
            "to": "14"
        },
        {
            "from": "10",
            "label": "5",
            "to": "22"
        },
        {
            "from": "10",
            "label": "5",
            "to": "23"
        },
        {
            "from": "10",
            "label": "3",
            "to": "25"
        },
        {
            "from": "10",
            "label": "4",
            "to": "28"
        },
        {
            "from": "9",
            "label": "5",
            "to": "26"
        },
        {
            "from": "9",
            "label": "3",
            "to": "40"
        },
        {
            "from": "9",
            "label": "5",
            "to": "35"
        },
        {
            "from": "9",
            "label": "5",
            "to": "5"
        },
        {
            "from": "9",
            "label": "5",
            "to": "16"
        },
        {
            "from": "9",
            "label": "3",
            "to": "2"
        },
        {
            "from": "9",
            "label": "3",
            "to": "29"
        },
        {
            "from": "9",
            "label": "3",
            "to": "17"
        },
        {
            "from": "9",
            "label": "5",
            "to": "19"
        },
        {
            "from": "9",
            "label": "5",
            "to": "11"
        },
        {
            "from": "9",
            "label": "5",
            "to": "4"
        },
        {
            "from": "9",
            "label": "3",
            "to": "38"
        },
        {
            "from": "9",
            "label": "3",
            "to": "20"
        },
        {
            "from": "9",
            "label": "5",
            "to": "23"
        },
        {
            "from": "9",
            "label": "5",
            "to": "34"
        },
        {
            "from": "9",
            "label": "3",
            "to": "1"
        },
        {
            "from": "9",
            "label": "3",
            "to": "12"
        },
        {
            "from": "9",
            "label": "5",
            "to": "36"
        },
        {
            "from": "9",
            "label": "5",
            "to": "7"
        },
        {
            "from": "9",
            "label": "5",
            "to": "28"
        },
        {
            "from": "9",
            "label": "4",
            "to": "13"
        },
        {
            "from": "9",
            "label": "4",
            "to": "32"
        },
        {
            "from": "9",
            "label": "4",
            "to": "8"
        },
        {
            "from": "9",
            "label": "5",
            "to": "14"
        },
        {
            "from": "9",
            "label": "4",
            "to": "10"
        },
        {
            "from": "9",
            "label": "3",
            "to": "6"
        },
        {
            "from": "9",
            "label": "4",
            "to": "18"
        },
        {
            "from": "9",
            "label": "3",
            "to": "24"
        },
        {
            "from": "9",
            "label": "5",
            "to": "30"
        },
        {
            "from": "9",
            "label": "3",
            "to": "9"
        },
        {
            "from": "8",
            "label": "5",
            "to": "11"
        },
        {
            "from": "8",
            "label": "5",
            "to": "28"
        },
        {
            "from": "8",
            "label": "3",
            "to": "4"
        },
        {
            "from": "8",
            "label": "3",
            "to": "34"
        },
        {
            "from": "8",
            "label": "5",
            "to": "20"
        },
        {
            "from": "8",
            "label": "5",
            "to": "22"
        },
        {
            "from": "8",
            "label": "3",
            "to": "23"
        },
        {
            "from": "8",
            "label": "4",
            "to": "8"
        },
        {
            "from": "8",
            "label": "4",
            "to": "5"
        },
        {
            "from": "8",
            "label": "5",
            "to": "17"
        },
        {
            "from": "8",
            "label": "5",
            "to": "7"
        },
        {
            "from": "8",
            "label": "4",
            "to": "9"
        },
        {
            "from": "8",
            "label": "3",
            "to": "1"
        },
        {
            "from": "8",
            "label": "5",
            "to": "24"
        },
        {
            "from": "8",
            "label": "3",
            "to": "10"
        },
        {
            "from": "8",
            "label": "5",
            "to": "25"
        },
        {
            "from": "8",
            "label": "5",
            "to": "32"
        },
        {
            "from": "8",
            "label": "4",
            "to": "13"
        },
        {
            "from": "8",
            "label": "5",
            "to": "15"
        },
        {
            "from": "8",
            "label": "5",
            "to": "39"
        },
        {
            "from": "8",
            "label": "3",
            "to": "30"
        },
        {
            "from": "7",
            "label": "4",
            "to": "19"
        },
        {
            "from": "7",
            "label": "3",
            "to": "29"
        },
        {
            "from": "7",
            "label": "5",
            "to": "39"
        },
        {
            "from": "7",
            "label": "3",
            "to": "26"
        },
        {
            "from": "7",
            "label": "5",
            "to": "40"
        },
        {
            "from": "7",
            "label": "3",
            "to": "11"
        },
        {
            "from": "7",
            "label": "3",
            "to": "32"
        },
        {
            "from": "7",
            "label": "4",
            "to": "22"
        },
        {
            "from": "7",
            "label": "4",
            "to": "27"
        },
        {
            "from": "7",
            "label": "4",
            "to": "8"
        },
        {
            "from": "7",
            "label": "4",
            "to": "31"
        },
        {
            "from": "7",
            "label": "5",
            "to": "30"
        },
        {
            "from": "7",
            "label": "5",
            "to": "7"
        },
        {
            "from": "7",
            "label": "5",
            "to": "38"
        },
        {
            "from": "7",
            "label": "5",
            "to": "14"
        },
        {
            "from": "7",
            "label": "3",
            "to": "13"
        },
        {
            "from": "7",
            "label": "4",
            "to": "34"
        },
        {
            "from": "7",
            "label": "3",
            "to": "37"
        },
        {
            "from": "7",
            "label": "5",
            "to": "6"
        },
        {
            "from": "7",
            "label": "5",
            "to": "28"
        },
        {
            "from": "7",
            "label": "4",
            "to": "17"
        },
        {
            "from": "6",
            "label": "4",
            "to": "3"
        },
        {
            "from": "6",
            "label": "3",
            "to": "29"
        },
        {
            "from": "6",
            "label": "5",
            "to": "21"
        },
        {
            "from": "6",
            "label": "5",
            "to": "36"
        },
        {
            "from": "6",
            "label": "4",
            "to": "4"
        },
        {
            "from": "6",
            "label": "3",
            "to": "31"
        },
        {
            "from": "6",
            "label": "5",
            "to": "28"
        },
        {
            "from": "6",
            "label": "5",
            "to": "32"
        },
        {
            "from": "6",
            "label": "5",
            "to": "6"
        },
        {
            "from": "6",
            "label": "3",
            "to": "9"
        },
        {
            "from": "6",
            "label": "5",
            "to": "38"
        },
        {
            "from": "6",
            "label": "5",
            "to": "35"
        },
        {
            "from": "6",
            "label": "5",
            "to": "15"
        },
        {
            "from": "6",
            "label": "3",
            "to": "16"
        },
        {
            "from": "6",
            "label": "5",
            "to": "14"
        },
        {
            "from": "6",
            "label": "5",
            "to": "12"
        },
        {
            "from": "6",
            "label": "5",
            "to": "1"
        },
        {
            "from": "6",
            "label": "5",
            "to": "39"
        },
        {
            "from": "6",
            "label": "3",
            "to": "34"
        },
        {
            "from": "6",
            "label": "5",
            "to": "26"
        },
        {
            "from": "6",
            "label": "5",
            "to": "18"
        },
        {
            "from": "6",
            "label": "5",
            "to": "25"
        },
        {
            "from": "6",
            "label": "5",
            "to": "5"
        },
        {
            "from": "5",
            "label": "5",
            "to": "26"
        },
        {
            "from": "5",
            "label": "4",
            "to": "35"
        },
        {
            "from": "5",
            "label": "3",
            "to": "40"
        },
        {
            "from": "5",
            "label": "4",
            "to": "32"
        },
        {
            "from": "5",
            "label": "5",
            "to": "3"
        },
        {
            "from": "5",
            "label": "5",
            "to": "10"
        },
        {
            "from": "5",
            "label": "5",
            "to": "22"
        },
        {
            "from": "5",
            "label": "5",
            "to": "5"
        },
        {
            "from": "5",
            "label": "5",
            "to": "6"
        },
        {
            "from": "5",
            "label": "5",
            "to": "14"
        },
        {
            "from": "5",
            "label": "3",
            "to": "20"
        },
        {
            "from": "5",
            "label": "3",
            "to": "2"
        },
        {
            "from": "5",
            "label": "5",
            "to": "18"
        },
        {
            "from": "5",
            "label": "5",
            "to": "24"
        },
        {
            "from": "5",
            "label": "3",
            "to": "4"
        },
        {
            "from": "5",
            "label": "5",
            "to": "23"
        },
        {
            "from": "5",
            "label": "3",
            "to": "13"
        },
        {
            "from": "5",
            "label": "4",
            "to": "39"
        },
        {
            "from": "5",
            "label": "3",
            "to": "19"
        },
        {
            "from": "5",
            "label": "3",
            "to": "1"
        },
        {
            "from": "5",
            "label": "5",
            "to": "7"
        },
        {
            "from": "5",
            "label": "5",
            "to": "12"
        },
        {
            "from": "4",
            "label": "4",
            "to": "36"
        },
        {
            "from": "4",
            "label": "5",
            "to": "1"
        },
        {
            "from": "4",
            "label": "3",
            "to": "22"
        },
        {
            "from": "4",
            "label": "3",
            "to": "37"
        },
        {
            "from": "4",
            "label": "4",
            "to": "32"
        },
        {
            "from": "4",
            "label": "5",
            "to": "38"
        },
        {
            "from": "4",
            "label": "3",
            "to": "9"
        },
        {
            "from": "4",
            "label": "4",
            "to": "35"
        },
        {
            "from": "4",
            "label": "3",
            "to": "39"
        },
        {
            "from": "4",
            "label": "4",
            "to": "6"
        },
        {
            "from": "4",
            "label": "5",
            "to": "19"
        },
        {
            "from": "4",
            "label": "5",
            "to": "40"
        },
        {
            "from": "4",
            "label": "5",
            "to": "21"
        },
        {
            "from": "4",
            "label": "4",
            "to": "14"
        },
        {
            "from": "4",
            "label": "5",
            "to": "20"
        },
        {
            "from": "4",
            "label": "5",
            "to": "29"
        },
        {
            "from": "4",
            "label": "5",
            "to": "23"
        },
        {
            "from": "4",
            "label": "5",
            "to": "24"
        },
        {
            "from": "4",
            "label": "5",
            "to": "17"
        },
        {
            "from": "4",
            "label": "4",
            "to": "2"
        },
        {
            "from": "4",
            "label": "5",
            "to": "34"
        },
        {
            "from": "4",
            "label": "4",
            "to": "28"
        },
        {
            "from": "4",
            "label": "5",
            "to": "4"
        },
        {
            "from": "4",
            "label": "5",
            "to": "5"
        },
        {
            "from": "3",
            "label": "5",
            "to": "20"
        },
        {
            "from": "3",
            "label": "3",
            "to": "19"
        },
        {
            "from": "3",
            "label": "3",
            "to": "4"
        },
        {
            "from": "3",
            "label": "3",
            "to": "23"
        },
        {
            "from": "3",
            "label": "3",
            "to": "7"
        },
        {
            "from": "3",
            "label": "3",
            "to": "31"
        },
        {
            "from": "3",
            "label": "5",
            "to": "29"
        },
        {
            "from": "3",
            "label": "3",
            "to": "35"
        },
        {
            "from": "3",
            "label": "4",
            "to": "6"
        },
        {
            "from": "3",
            "label": "5",
            "to": "2"
        },
        {
            "from": "3",
            "label": "4",
            "to": "18"
        },
        {
            "from": "3",
            "label": "5",
            "to": "12"
        },
        {
            "from": "3",
            "label": "4",
            "to": "39"
        },
        {
            "from": "3",
            "label": "3",
            "to": "24"
        },
        {
            "from": "3",
            "label": "4",
            "to": "26"
        },
        {
            "from": "3",
            "label": "5",
            "to": "8"
        },
        {
            "from": "3",
            "label": "5",
            "to": "30"
        },
        {
            "from": "3",
            "label": "4",
            "to": "40"
        },
        {
            "from": "3",
            "label": "3",
            "to": "28"
        },
        {
            "from": "3",
            "label": "5",
            "to": "32"
        },
        {
            "from": "2",
            "label": "5",
            "to": "2"
        },
        {
            "from": "2",
            "label": "4",
            "to": "38"
        },
        {
            "from": "2",
            "label": "4",
            "to": "22"
        },
        {
            "from": "2",
            "label": "5",
            "to": "40"
        },
        {
            "from": "2",
            "label": "5",
            "to": "30"
        },
        {
            "from": "2",
            "label": "4",
            "to": "17"
        },
        {
            "from": "2",
            "label": "5",
            "to": "9"
        },
        {
            "from": "2",
            "label": "5",
            "to": "4"
        },
        {
            "from": "2",
            "label": "5",
            "to": "5"
        },
        {
            "from": "2",
            "label": "3",
            "to": "33"
        },
        {
            "from": "2",
            "label": "5",
            "to": "25"
        },
        {
            "from": "2",
            "label": "3",
            "to": "13"
        },
        {
            "from": "2",
            "label": "3",
            "to": "27"
        },
        {
            "from": "2",
            "label": "5",
            "to": "6"
        },
        {
            "from": "2",
            "label": "5",
            "to": "12"
        },
        {
            "from": "2",
            "label": "4",
            "to": "7"
        },
        {
            "from": "2",
            "label": "5",
            "to": "14"
        },
        {
            "from": "2",
            "label": "5",
            "to": "23"
        },
        {
            "from": "2",
            "label": "5",
            "to": "32"
        },
        {
            "from": "2",
            "label": "3",
            "to": "10"
        },
        {
            "from": "1",
            "label": "3",
            "to": "22"
        },
        {
            "from": "1",
            "label": "3",
            "to": "39"
        },
        {
            "from": "1",
            "label": "3",
            "to": "38"
        },
        {
            "from": "1",
            "label": "5",
            "to": "10"
        },
        {
            "from": "1",
            "label": "3",
            "to": "3"
        },
        {
            "from": "1",
            "label": "5",
            "to": "29"
        },
        {
            "from": "1",
            "label": "4",
            "to": "4"
        },
        {
            "from": "1",
            "label": "3",
            "to": "33"
        },
        {
            "from": "1",
            "label": "4",
            "to": "9"
        },
        {
            "from": "1",
            "label": "5",
            "to": "15"
        },
        {
            "from": "1",
            "label": "4",
            "to": "12"
        },
        {
            "from": "1",
            "label": "3",
            "to": "37"
        },
        {
            "from": "1",
            "label": "4",
            "to": "20"
        },
        {
            "from": "1",
            "label": "3",
            "to": "18"
        },
        {
            "from": "1",
            "label": "3",
            "to": "7"
        },
        {
            "from": "1",
            "label": "5",
            "to": "11"
        },
        {
            "from": "1",
            "label": "3",
            "to": "32"
        },
        {
            "from": "1",
            "label": "4",
            "to": "17"
        },
        {
            "from": "1",
            "label": "5",
            "to": "21"
        },
        {
            "from": "1",
            "label": "5",
            "to": "23"
        },
        {
            "from": "1",
            "label": "4",
            "to": "31"
        },
        {
            "from": "1",
            "label": "4",
            "to": "26"
        },
        {
            "from": "1",
            "label": "4",
            "to": "34"
        },
        {
            "from": "1",
            "label": "5",
            "to": "27"
        },
        {
            "from": "1",
            "label": "4",
            "to": "28"
        },
        {
            "from": "1",
            "label": "5",
            "to": "40"
        },
        {
            "from": "1",
            "label": "3",
            "to": "30"
        },
        {
            "from": "1",
            "label": "4",
            "to": "14"
        },
        {
            "from": "1",
            "label": "3",
            "to": "1"
        },
        {
            "from": "1",
            "label": "4",
            "to": "16"
        },
        {
            "from": "1",
            "label": "5",
            "to": "41"
        }
    ],
    "nodes": [
        {
            "group": "usuario",
            "id": "26",
            "label": "Santiago"
        },
        {
            "group": "usuario",
            "id": "25",
            "label": "Pablo"
        },
        {
            "group": "usuario",
            "id": "24",
            "label": "Mike"
        },
        {
            "group": "usuario",
            "id": "23",
            "label": "Aleja"
        },
        {
            "group": "usuario",
            "id": "22",
            "label": "Alejandro"
        },
        {
            "group": "usuario",
            "id": "21",
            "label": "Gabi"
        },
        {
            "group": "usuario",
            "id": "20",
            "label": "Mara"
        },
        {
            "group": "usuario",
            "id": "19",
            "label": "Paula"
        },
        {
            "group": "usuario",
            "id": "18",
            "label": "Gina"
        },
        {
            "group": "usuario",
            "id": "17",
            "label": "Cristian"
        },
        {
            "group": "usuario",
            "id": "16",
            "label": "Nestor"
        },
        {
            "group": "usuario",
            "id": "15",
            "label": "Dante"
        },
        {
            "group": "usuario",
            "id": "14",
            "label": "Bart"
        },
        {
            "group": "usuario",
            "id": "13",
            "label": "Gabriel"
        },
        {
            "group": "usuario",
            "id": "12",
            "label": "Jorge"
        },
        {
            "group": "usuario",
            "id": "11",
            "label": "Felipe"
        },
        {
            "group": "usuario",
            "id": "10",
            "label": "Danna"
        },
        {
            "group": "usuario",
            "id": "9",
            "label": "Maxi"
        },
        {
            "group": "usuario",
            "id": "8",
            "label": "Maira"
        },
        {
            "group": "usuario",
            "id": "7",
            "label": "Brahian"
        },
        {
            "group": "usuario",
            "id": "6",
            "label": "Janer"
        },
        {
            "group": "usuario",
            "id": "5",
            "label": "Hanner"
        },
        {
            "group": "usuario",
            "id": "4",
            "label": "Derly"
        },
        {
            "group": "usuario",
            "id": "3",
            "label": "Manu"
        },
        {
            "group": "usuario",
            "id": "2",
            "label": "Pedro"
        },
        {
            "group": "usuario",
            "id": "1",
            "label": "Juan"
        },
        {
            "group": "cancion",
            "id": "41",
            "label": "Carrao"
        },
        {
            "group": "cancion",
            "id": "40",
            "label": "Falling forever"
        },
        {
            "group": "cancion",
            "id": "39",
            "label": "Fotografia"
        },
        {
            "group": "cancion",
            "id": "38",
            "label": "Un ratito"
        },
        {
            "group": "cancion",
            "id": "37",
            "label": "Viva las vegas"
        },
        {
            "group": "cancion",
            "id": "36",
            "label": "La noche mas linda"
        },
        {
            "group": "cancion",
            "id": "35",
            "label": "Entre dos tierras"
        },
        {
            "group": "cancion",
            "id": "34",
            "label": "No tiene sentido"
        },
        {
            "group": "cancion",
            "id": "33",
            "label": "Cosa de locos"
        },
        {
            "group": "cancion",
            "id": "32",
            "label": "Como pasa el tiempo"
        },
        {
            "group": "cancion",
            "id": "31",
            "label": "Seal de vida"
        },
        {
            "group": "cancion",
            "id": "30",
            "label": "Reload"
        },
        {
            "group": "cancion",
            "id": "29",
            "label": "Main title"
        },
        {
            "group": "cancion",
            "id": "28",
            "label": "El doctorado"
        },
        {
            "group": "cancion",
            "id": "27",
            "label": "Otra como tu"
        },
        {
            "group": "cancion",
            "id": "26",
            "label": "Rojo"
        },
        {
            "group": "cancion",
            "id": "25",
            "label": "Neverland"
        },
        {
            "group": "cancion",
            "id": "24",
            "label": "Make it bun dem"
        },
        {
            "group": "cancion",
            "id": "23",
            "label": "Fuimos amor"
        },
        {
            "group": "cancion",
            "id": "22",
            "label": "Tu me quemas"
        },
        {
            "group": "cancion",
            "id": "21",
            "label": "Ella baila sola"
        },
        {
            "group": "cancion",
            "id": "20",
            "label": "Tu misterioso alguien"
        },
        {
            "group": "cancion",
            "id": "19",
            "label": "Doing time "
        },
        {
            "group": "cancion",
            "id": "18",
            "label": "Lamento boliviano"
        },
        {
            "group": "cancion",
            "id": "17",
            "label": "Feliz Cumpleaos"
        },
        {
            "group": "cancion",
            "id": "16",
            "label": "Espresso"
        },
        {
            "group": "cancion",
            "id": "15",
            "label": "Oki doki"
        },
        {
            "group": "cancion",
            "id": "14",
            "label": "Holdin' On"
        },
        {
            "group": "cancion",
            "id": "13",
            "label": "I love it"
        },
        {
            "group": "cancion",
            "id": "12",
            "label": "What do you mean?"
        },
        {
            "group": "cancion",
            "id": "11",
            "label": "Debajo del sombrero"
        },
        {
            "group": "cancion",
            "id": "10",
            "label": "The fate of ophleia"
        },
        {
            "group": "cancion",
            "id": "9",
            "label": "Primera Cita"
        },
        {
            "group": "cancion",
            "id": "8",
            "label": "Coqueta"
        },
        {
            "group": "cancion",
            "id": "7",
            "label": "Me volviero a hablar de ella"
        },
        {
            "group": "cancion",
            "id": "6",
            "label": "Firework"
        },
        {
            "group": "cancion",
            "id": "5",
            "label": "Golden"
        },
        {
            "group": "cancion",
            "id": "4",
            "label": "A veces"
        },
        {
            "group": "cancion",
            "id": "3",
            "label": "No es justo"
        },
        {
            "group": "cancion",
            "id": "2",
            "label": "Do ya wanna taste it"
        },
        {
            "group": "cancion",
            "id": "1",
            "label": "High and low"
        }
    ]
}
